common/__init__.py
common/calculator.py
common/plotter.py
common/rootutils.py
common/utils.py
pyutils_hep-0.1.14.dist-info/licenses/LICENSE
snowflake/__init__.py
snowflake/dirs.py
snowflake/library.py
snowflake/llh.py
snowflake/shoveler.py
snowflake/standalone.py
snowflake/unfold.py
t2k/__init__.py
t2k/directories.py
t2k/submit.py
t2k/analysis/Base.py
t2k/analysis/P0DCutUtils.py
t2k/analysis/__init__.py
t2k/analysis/binning.py
t2k/analysis/constants.py
t2k/analysis/highland_configurations.py
t2k/analysis/makePlots.py
t2k/analysis/sortdicts.py
t2k/analysis/submit_analysis.py
t2k/analysis/utils.py
t2k/analysis/varstrings.py
t2k/bin/cmttags.py
t2k/bin/submit_scripts.py
t2k/production/README.md
t2k/production/__init__.py
t2k/production/bin/CountDirMissing.py
t2k/production/bin/CreateCfgFile.py
t2k/production/bin/CreateDirs.py
t2k/production/bin/Purge.py
t2k/production/bin/PurgeFromGrid.py
t2k/production/bin/SubmitND280Jobs.py
t2k/production/bin/checksize.py
t2k/production/flux/__init__.py
t2k/production/flux/bin/haddFlux.py
t2k/production/flux/bin/makeGENIESetup.py
t2k/production/flux/templates/genie_setup_flux_probs.cfg
t2k/production/flux/templates/template_script.sh
t2k/production/lib/MCConfigClass.py
t2k/production/lib/MCJobClass.py
t2k/production/lib/__init__.py
t2k/production/lib/utils.py
thirdparty/__init__.py
thirdparty/autovivification.py
thirdparty/elements.py
thirdparty/utils.py
pyutils_hep-0.1.14.dist-info/METADATA
pyutils_hep-0.1.14.dist-info/WHEEL
pyutils_hep-0.1.14.dist-info/top_level.txt
pyutils_hep-0.1.14.dist-info/RECORD
