Metadata-Version: 2.4
Name: pyutils_hep
Version: 0.1.14
Summary: A package with useful python utilities for neutrino physics
Author-email: Tianlu Yuan <tyuan@icecube.wisc.edu>
License: MIT License
Project-URL: Repository, https://github.com/tianluyuan/pyutils
Classifier: Intended Audience :: Science/Research
Classifier: License :: OSI Approved :: MIT License
Classifier: Natural Language :: English
Classifier: Programming Language :: Python :: 3
Classifier: Operating System :: MacOS :: MacOS X
Classifier: Operating System :: POSIX :: Linux
Classifier: Topic :: Scientific/Engineering
Requires-Python: >=3.8
License-File: LICENSE
Requires-Dist: numpy>=1.17
Requires-Dist: scipy
Provides-Extra: plotting
Requires-Dist: matplotlib; extra == "plotting"
Dynamic: license-file
